<?xml version='1.0' encoding='UTF-8'?>
<ExchangeRatesByDateResult xmlns="http://www.cba.am/" xmlns:soap="http://schemas.xmlsoap.org/soap/envelope/" xmlns:xsi="http://www.w3.org/2001/XMLSchema-instance" xmlns:xsd="http://www.w3.org/2001/XMLSchema">
  <CurrentDate>2000-09-20T00:00:00</CurrentDate>
  <NextAvailableDate>2000-09-22T00:00:00</NextAvailableDate>
  <PreviousAvailableDate>2000-09-19T00:00:00</PreviousAvailableDate>
  <Rates>
    <ExchangeRate>
      <ISO>USD</ISO>
      <Amount>1</Amount>
      <Rate>538.9000</Rate>
      <Difference>-0.3700</Difference>
    </ExchangeRate>
    <ExchangeRate>
      <ISO>GBP</ISO>
      <Amount>1</Amount>
      <Rate>755.3800</Rate>
      <Difference>1.1000</Difference>
    </ExchangeRate>
    <ExchangeRate>
      <ISO>AUD</ISO>
      <Amount>1</Amount>
      <Rate>292.7300</Rate>
      <Difference>-0.7400</Difference>
    </ExchangeRate>
    <ExchangeRate>
      <ISO>ATS</ISO>
      <Amount>1</Amount>
      <Rate>33.3900</Rate>
      <Difference>-0.3700</Difference>
    </ExchangeRate>
    <ExchangeRate>
      <ISO>ARP</ISO>
      <Amount>1</Amount>
      <Rate>539.0100</Rate>
      <Difference>-0.8100</Difference>
    </ExchangeRate>
    <ExchangeRate>
      <ISO>BEF</ISO>
      <Amount>10</Amount>
      <Rate>113.9000</Rate>
      <Difference>-1.2700</Difference>
    </ExchangeRate>
    <ExchangeRate>
      <ISO>DEM</ISO>
      <Amount>1</Amount>
      <Rate>234.9200</Rate>
      <Difference>-2.6200</Difference>
    </ExchangeRate>
    <ExchangeRate>
      <ISO>DKK</ISO>
      <Amount>1</Amount>
      <Rate>61.5200</Rate>
      <Difference>-0.1900</Difference>
    </ExchangeRate>
    <ExchangeRate>
      <ISO>EGP</ISO>
      <Amount>1</Amount>
      <Rate>151.2000</Rate>
      <Difference>1.0800</Difference>
    </ExchangeRate>
    <ExchangeRate>
      <ISO>EUR</ISO>
      <Amount>1</Amount>
      <Rate>459.4700</Rate>
      <Difference>-5.1100</Difference>
    </ExchangeRate>
    <ExchangeRate>
      <ISO>SDR</ISO>
      <Amount>1</Amount>
      <Rate>716.7600</Rate>
      <Difference>0.0000</Difference>
    </ExchangeRate>
    <ExchangeRate>
      <ISO>TRL</ISO>
      <Amount>1000</Amount>
      <Rate>8.0400</Rate>
      <Difference>-0.0500</Difference>
    </ExchangeRate>
    <ExchangeRate>
      <ISO>IEP</ISO>
      <Amount>1</Amount>
      <Rate>583.4000</Rate>
      <Difference>-6.5000</Difference>
    </ExchangeRate>
    <ExchangeRate>
      <ISO>IRR</ISO>
      <Amount>100</Amount>
      <Rate>30.1500</Rate>
      <Difference>0.0000</Difference>
    </ExchangeRate>
    <ExchangeRate>
      <ISO>ESP</ISO>
      <Amount>10</Amount>
      <Rate>27.6100</Rate>
      <Difference>-0.3100</Difference>
    </ExchangeRate>
    <ExchangeRate>
      <ISO>ILS</ISO>
      <Amount>1</Amount>
      <Rate>132.9600</Rate>
      <Difference>-0.5600</Difference>
    </ExchangeRate>
    <ExchangeRate>
      <ISO>ITL</ISO>
      <Amount>100</Amount>
      <Rate>23.7300</Rate>
      <Difference>-0.2600</Difference>
    </ExchangeRate>
    <ExchangeRate>
      <ISO>PLZ</ISO>
      <Amount>1</Amount>
      <Rate>117.4000</Rate>
      <Difference>-1.3200</Difference>
    </ExchangeRate>
    <ExchangeRate>
      <ISO>LBP</ISO>
      <Amount>100</Amount>
      <Rate>35.7500</Rate>
      <Difference>-0.0200</Difference>
    </ExchangeRate>
    <ExchangeRate>
      <ISO>CAD</ISO>
      <Amount>1</Amount>
      <Rate>361.9000</Rate>
      <Difference>-1.4200</Difference>
    </ExchangeRate>
    <ExchangeRate>
      <ISO>INR</ISO>
      <Amount>1</Amount>
      <Rate>11.6600</Rate>
      <Difference>-0.1000</Difference>
    </ExchangeRate>
    <ExchangeRate>
      <ISO>NLG</ISO>
      <Amount>1</Amount>
      <Rate>208.5000</Rate>
      <Difference>-2.3200</Difference>
    </ExchangeRate>
    <ExchangeRate>
      <ISO>GRD</ISO>
      <Amount>10</Amount>
      <Rate>13.6000</Rate>
      <Difference>-0.1600</Difference>
    </ExchangeRate>
    <ExchangeRate>
      <ISO>HUF</ISO>
      <Amount>10</Amount>
      <Rate>17.5200</Rate>
      <Difference>-0.1100</Difference>
    </ExchangeRate>
    <ExchangeRate>
      <ISO>JPY</ISO>
      <Amount>10</Amount>
      <Rate>50.4000</Rate>
      <Difference>-0.0100</Difference>
    </ExchangeRate>
    <ExchangeRate>
      <ISO>NOK</ISO>
      <Amount>1</Amount>
      <Rate>57.5000</Rate>
      <Difference>-0.4400</Difference>
    </ExchangeRate>
    <ExchangeRate>
      <ISO>SEK</ISO>
      <Amount>1</Amount>
      <Rate>54.7400</Rate>
      <Difference>-0.6200</Difference>
    </ExchangeRate>
    <ExchangeRate>
      <ISO>CHF</ISO>
      <Amount>1</Amount>
      <Rate>301.5900</Rate>
      <Difference>-2.5000</Difference>
    </ExchangeRate>
    <ExchangeRate>
      <ISO>CZK</ISO>
      <Amount>1</Amount>
      <Rate>12.9400</Rate>
      <Difference>0.0100</Difference>
    </ExchangeRate>
    <ExchangeRate>
      <ISO>CNY</ISO>
      <Amount>1</Amount>
      <Rate>65.1000</Rate>
      <Difference>-0.0500</Difference>
    </ExchangeRate>
    <ExchangeRate>
      <ISO>PTE</ISO>
      <Amount>10</Amount>
      <Rate>22.9200</Rate>
      <Difference>-0.2500</Difference>
    </ExchangeRate>
    <ExchangeRate>
      <ISO>SGD</ISO>
      <Amount>1</Amount>
      <Rate>308.6100</Rate>
      <Difference>-0.2100</Difference>
    </ExchangeRate>
    <ExchangeRate>
      <ISO>SKK</ISO>
      <Amount>1</Amount>
      <Rate>10.6700</Rate>
      <Difference>-0.0800</Difference>
    </ExchangeRate>
    <ExchangeRate>
      <ISO>FIM</ISO>
      <Amount>1</Amount>
      <Rate>77.2800</Rate>
      <Difference>-0.8600</Difference>
    </ExchangeRate>
    <ExchangeRate>
      <ISO>FRF</ISO>
      <Amount>1</Amount>
      <Rate>70.0500</Rate>
      <Difference>-0.7700</Difference>
    </ExchangeRate>
    <ExchangeRate>
      <ISO>KRW</ISO>
      <Amount>100</Amount>
      <Rate>48.2100</Rate>
      <Difference>-0.2200</Difference>
    </ExchangeRate>
    <ExchangeRate>
      <ISO>BRC</ISO>
      <Amount>1</Amount>
      <Rate>290.0600</Rate>
      <Difference>-2.3000</Difference>
    </ExchangeRate>
    <ExchangeRate>
      <ISO>MXN</ISO>
      <Amount>1</Amount>
      <Rate>57.1800</Rate>
      <Difference>-0.4400</Difference>
    </ExchangeRate>
    <ExchangeRate>
      <ISO>SAR</ISO>
      <Amount>1</Amount>
      <Rate>143.6900</Rate>
      <Difference>-0.1000</Difference>
    </ExchangeRate>
    <ExchangeRate>
      <ISO>SYP</ISO>
      <Amount>1</Amount>
      <Rate>11.9800</Rate>
      <Difference>0.0000</Difference>
    </ExchangeRate>
    <ExchangeRate>
      <ISO>AED</ISO>
      <Amount>1</Amount>
      <Rate>146.7600</Rate>
      <Difference>-0.1000</Difference>
    </ExchangeRate>
    <ExchangeRate>
      <ISO>KWD</ISO>
      <Amount>1</Amount>
      <Rate>1744.5800</Rate>
      <Difference>-2.1700</Difference>
    </ExchangeRate>
    <ExchangeRate>
      <ISO>BGL</ISO>
      <Amount>1</Amount>
      <Rate>234.9200</Rate>
      <Difference>-2.6200</Difference>
    </ExchangeRate>
    <ExchangeRate>
      <ISO>ROL</ISO>
      <Amount>1000</Amount>
      <Rate>22.7200</Rate>
      <Difference>-0.0600</Difference>
    </ExchangeRate>
    <ExchangeRate>
      <ISO>ISK</ISO>
      <Amount>1</Amount>
      <Rate>63.5400</Rate>
      <Difference>-0.3500</Difference>
    </ExchangeRate>
    <ExchangeRate>
      <ISO>EEK</ISO>
      <Amount>1</Amount>
      <Rate>29.4600</Rate>
      <Difference>-0.0200</Difference>
    </ExchangeRate>
    <ExchangeRate>
      <ISO>LVL</ISO>
      <Amount>1</Amount>
      <Rate>865.0100</Rate>
      <Difference>-1.9800</Difference>
    </ExchangeRate>
    <ExchangeRate>
      <ISO>LTL</ISO>
      <Amount>1</Amount>
      <Rate>134.7300</Rate>
      <Difference>-0.0900</Difference>
    </ExchangeRate>
    <ExchangeRate>
      <ISO>KGS</ISO>
      <Amount>1</Amount>
      <Rate>11.0900</Rate>
      <Difference>0.0000</Difference>
    </ExchangeRate>
    <ExchangeRate>
      <ISO>KZT</ISO>
      <Amount>1</Amount>
      <Rate>37.7600</Rate>
      <Difference>-0.0300</Difference>
    </ExchangeRate>
    <ExchangeRate>
      <ISO>MDL</ISO>
      <Amount>1</Amount>
      <Rate>43.7000</Rate>
      <Difference>0.0400</Difference>
    </ExchangeRate>
    <ExchangeRate>
      <ISO>RUR</ISO>
      <Amount>1</Amount>
      <Rate>19.4000</Rate>
      <Difference>-0.1000</Difference>
    </ExchangeRate>
    <ExchangeRate>
      <ISO>UAH</ISO>
      <Amount>1</Amount>
      <Rate>99.0800</Rate>
      <Difference>-0.0700</Difference>
    </ExchangeRate>
    <ExchangeRate>
      <ISO>USM</ISO>
      <Amount>1</Amount>
      <Rate>18.9700</Rate>
      <Difference>-0.0100</Difference>
    </ExchangeRate>
    <ExchangeRate>
      <ISO>BYR</ISO>
      <Amount>10</Amount>
      <Rate>5.2600</Rate>
      <Difference>-0.0100</Difference>
    </ExchangeRate>
    <ExchangeRate>
      <ISO>TAD</ISO>
      <Amount>10</Amount>
      <Rate>27.8200</Rate>
      <Difference>-0.0200</Difference>
    </ExchangeRate>
    <ExchangeRate>
      <ISO>TMM</ISO>
      <Amount>100</Amount>
      <Rate>10.3600</Rate>
      <Difference>-0.0100</Difference>
    </ExchangeRate>
    <ExchangeRate>
      <ISO>GEL</ISO>
      <Amount>1</Amount>
      <Rate>274.9500</Rate>
      <Difference>-0.1900</Difference>
    </ExchangeRate>
    <ExchangeRate>
      <ISO>TJS</ISO>
      <Amount>10</Amount>
      <Rate>27.8200</Rate>
      <Difference>-0.0200</Difference>
    </ExchangeRate>
    <ExchangeRate>
      <ISO>TMT</ISO>
      <Amount>100</Amount>
      <Rate>10.3600</Rate>
      <Difference>-0.0100</Difference>
    </ExchangeRate>
  </Rates>
</ExchangeRatesByDateResult>
