<?xml version='1.0' encoding='UTF-8'?>
<ExchangeRatesByDateResult xmlns="http://www.cba.am/" xmlns:soap="http://schemas.xmlsoap.org/soap/envelope/" xmlns:xsi="http://www.w3.org/2001/XMLSchema-instance" xmlns:xsd="http://www.w3.org/2001/XMLSchema">
  <CurrentDate>2004-11-15T00:00:00</CurrentDate>
  <NextAvailableDate>2004-11-16T00:00:00</NextAvailableDate>
  <PreviousAvailableDate>2004-11-12T00:00:00</PreviousAvailableDate>
  <Rates>
    <ExchangeRate>
      <ISO>USD</ISO>
      <Amount>1</Amount>
      <Rate>503.1600</Rate>
      <Difference>-0.3100</Difference>
    </ExchangeRate>
    <ExchangeRate>
      <ISO>GBP</ISO>
      <Amount>1</Amount>
      <Rate>929.2359</Rate>
      <Difference>1.5924</Difference>
    </ExchangeRate>
    <ExchangeRate>
      <ISO>AUD</ISO>
      <Amount>1</Amount>
      <Rate>385.2696</Rate>
      <Difference>2.7834</Difference>
    </ExchangeRate>
    <ExchangeRate>
      <ISO>ARP</ISO>
      <Amount>1</Amount>
      <Rate>169.8430</Rate>
      <Difference>-0.2482</Difference>
    </ExchangeRate>
    <ExchangeRate>
      <ISO>BEF</ISO>
      <Amount>10</Amount>
      <Rate>0.0000</Rate>
      <Difference>0.0000</Difference>
    </ExchangeRate>
    <ExchangeRate>
      <ISO>DEM</ISO>
      <Amount>1</Amount>
      <Rate>0.0000</Rate>
      <Difference>0.0000</Difference>
    </ExchangeRate>
    <ExchangeRate>
      <ISO>DKK</ISO>
      <Amount>1</Amount>
      <Rate>87.4985</Rate>
      <Difference>0.3100</Difference>
    </ExchangeRate>
    <ExchangeRate>
      <ISO>EGP</ISO>
      <Amount>1</Amount>
      <Rate>80.8614</Rate>
      <Difference>-0.0498</Difference>
    </ExchangeRate>
    <ExchangeRate>
      <ISO>EUR</ISO>
      <Amount>1</Amount>
      <Rate>650.1330</Rate>
      <Difference>1.1602</Difference>
    </ExchangeRate>
    <ExchangeRate>
      <ISO>SDR</ISO>
      <Amount>1</Amount>
      <Rate>755.7900</Rate>
      <Difference>0.0000</Difference>
    </ExchangeRate>
    <ExchangeRate>
      <ISO>TRL</ISO>
      <Amount>1000</Amount>
      <Rate>3.4586</Rate>
      <Difference>-0.0032</Difference>
    </ExchangeRate>
    <ExchangeRate>
      <ISO>IRR</ISO>
      <Amount>100</Amount>
      <Rate>5.7242</Rate>
      <Difference>-0.0055</Difference>
    </ExchangeRate>
    <ExchangeRate>
      <ISO>ESP</ISO>
      <Amount>10</Amount>
      <Rate>0.0000</Rate>
      <Difference>0.0000</Difference>
    </ExchangeRate>
    <ExchangeRate>
      <ISO>ILS</ISO>
      <Amount>1</Amount>
      <Rate>113.6058</Rate>
      <Difference>-0.5339</Difference>
    </ExchangeRate>
    <ExchangeRate>
      <ISO>ITL</ISO>
      <Amount>100</Amount>
      <Rate>0.0000</Rate>
      <Difference>0.0000</Difference>
    </ExchangeRate>
    <ExchangeRate>
      <ISO>PLZ</ISO>
      <Amount>1</Amount>
      <Rate>151.6227</Rate>
      <Difference>-1.0133</Difference>
    </ExchangeRate>
    <ExchangeRate>
      <ISO>LBP</ISO>
      <Amount>100</Amount>
      <Rate>33.3771</Rate>
      <Difference>-0.0206</Difference>
    </ExchangeRate>
    <ExchangeRate>
      <ISO>CAD</ISO>
      <Amount>1</Amount>
      <Rate>420.0000</Rate>
      <Difference>-0.2588</Difference>
    </ExchangeRate>
    <ExchangeRate>
      <ISO>INR</ISO>
      <Amount>1</Amount>
      <Rate>11.1714</Rate>
      <Difference>0.0203</Difference>
    </ExchangeRate>
    <ExchangeRate>
      <ISO>NLG</ISO>
      <Amount>1</Amount>
      <Rate>0.0000</Rate>
      <Difference>0.0000</Difference>
    </ExchangeRate>
    <ExchangeRate>
      <ISO>GRD</ISO>
      <Amount>10</Amount>
      <Rate>0.0000</Rate>
      <Difference>0.0000</Difference>
    </ExchangeRate>
    <ExchangeRate>
      <ISO>HUF</ISO>
      <Amount>10</Amount>
      <Rate>26.5730</Rate>
      <Difference>0.0690</Difference>
    </ExchangeRate>
    <ExchangeRate>
      <ISO>JPY</ISO>
      <Amount>10</Amount>
      <Rate>47.1742</Rate>
      <Difference>0.1121</Difference>
    </ExchangeRate>
    <ExchangeRate>
      <ISO>NOK</ISO>
      <Amount>1</Amount>
      <Rate>79.6278</Rate>
      <Difference>-0.2640</Difference>
    </ExchangeRate>
    <ExchangeRate>
      <ISO>SEK</ISO>
      <Amount>1</Amount>
      <Rate>71.8776</Rate>
      <Difference>-0.1847</Difference>
    </ExchangeRate>
    <ExchangeRate>
      <ISO>CHF</ISO>
      <Amount>1</Amount>
      <Rate>426.9457</Rate>
      <Difference>-2.2706</Difference>
    </ExchangeRate>
    <ExchangeRate>
      <ISO>CZK</ISO>
      <Amount>1</Amount>
      <Rate>20.6518</Rate>
      <Difference>0.0596</Difference>
    </ExchangeRate>
    <ExchangeRate>
      <ISO>CNY</ISO>
      <Amount>1</Amount>
      <Rate>60.7938</Rate>
      <Difference>-0.0375</Difference>
    </ExchangeRate>
    <ExchangeRate>
      <ISO>PTE</ISO>
      <Amount>10</Amount>
      <Rate>0.0000</Rate>
      <Difference>0.0000</Difference>
    </ExchangeRate>
    <ExchangeRate>
      <ISO>SGD</ISO>
      <Amount>1</Amount>
      <Rate>304.2632</Rate>
      <Difference>0.4556</Difference>
    </ExchangeRate>
    <ExchangeRate>
      <ISO>SKK</ISO>
      <Amount>1</Amount>
      <Rate>16.4024</Rate>
      <Difference>0.0406</Difference>
    </ExchangeRate>
    <ExchangeRate>
      <ISO>FIM</ISO>
      <Amount>1</Amount>
      <Rate>0.0000</Rate>
      <Difference>0.0000</Difference>
    </ExchangeRate>
    <ExchangeRate>
      <ISO>FRF</ISO>
      <Amount>1</Amount>
      <Rate>0.0000</Rate>
      <Difference>0.0000</Difference>
    </ExchangeRate>
    <ExchangeRate>
      <ISO>KRW</ISO>
      <Amount>100</Amount>
      <Rate>45.5596</Rate>
      <Difference>0.2387</Difference>
    </ExchangeRate>
    <ExchangeRate>
      <ISO>BRC</ISO>
      <Amount>1</Amount>
      <Rate>178.5420</Rate>
      <Difference>-0.1100</Difference>
    </ExchangeRate>
    <ExchangeRate>
      <ISO>MXN</ISO>
      <Amount>1</Amount>
      <Rate>44.7651</Rate>
      <Difference>-0.0276</Difference>
    </ExchangeRate>
    <ExchangeRate>
      <ISO>SAR</ISO>
      <Amount>1</Amount>
      <Rate>134.1760</Rate>
      <Difference>-0.0827</Difference>
    </ExchangeRate>
    <ExchangeRate>
      <ISO>SYP</ISO>
      <Amount>1</Amount>
      <Rate>9.6873</Rate>
      <Difference>-0.0060</Difference>
    </ExchangeRate>
    <ExchangeRate>
      <ISO>AED</ISO>
      <Amount>1</Amount>
      <Rate>136.9944</Rate>
      <Difference>-0.0844</Difference>
    </ExchangeRate>
    <ExchangeRate>
      <ISO>KWD</ISO>
      <Amount>1</Amount>
      <Rate>1667.7494</Rate>
      <Difference>-1.0275</Difference>
    </ExchangeRate>
    <ExchangeRate>
      <ISO>BGL</ISO>
      <Amount>1</Amount>
      <Rate>331.6110</Rate>
      <Difference>-2.4433</Difference>
    </ExchangeRate>
    <ExchangeRate>
      <ISO>ROL</ISO>
      <Amount>1000</Amount>
      <Rate>15.2400</Rate>
      <Difference>0.0000</Difference>
    </ExchangeRate>
    <ExchangeRate>
      <ISO>ISK</ISO>
      <Amount>1</Amount>
      <Rate>74.5422</Rate>
      <Difference>0.3825</Difference>
    </ExchangeRate>
    <ExchangeRate>
      <ISO>EEK</ISO>
      <Amount>1</Amount>
      <Rate>41.5591</Rate>
      <Difference>0.1014</Difference>
    </ExchangeRate>
    <ExchangeRate>
      <ISO>LVL</ISO>
      <Amount>1</Amount>
      <Rate>945.7895</Rate>
      <Difference>-2.3649</Difference>
    </ExchangeRate>
    <ExchangeRate>
      <ISO>LTL</ISO>
      <Amount>1</Amount>
      <Rate>187.8023</Rate>
      <Difference>0.0454</Difference>
    </ExchangeRate>
    <ExchangeRate>
      <ISO>KGS</ISO>
      <Amount>1</Amount>
      <Rate>12.1034</Rate>
      <Difference>0.0162</Difference>
    </ExchangeRate>
    <ExchangeRate>
      <ISO>KZT</ISO>
      <Amount>1</Amount>
      <Rate>38.3477</Rate>
      <Difference>-0.0236</Difference>
    </ExchangeRate>
    <ExchangeRate>
      <ISO>MDL</ISO>
      <Amount>1</Amount>
      <Rate>40.2960</Rate>
      <Difference>-0.0264</Difference>
    </ExchangeRate>
    <ExchangeRate>
      <ISO>RUR</ISO>
      <Amount>1</Amount>
      <Rate>17.5531</Rate>
      <Difference>-0.0067</Difference>
    </ExchangeRate>
    <ExchangeRate>
      <ISO>UAH</ISO>
      <Amount>1</Amount>
      <Rate>94.8231</Rate>
      <Difference>-0.0585</Difference>
    </ExchangeRate>
    <ExchangeRate>
      <ISO>USM</ISO>
      <Amount>1</Amount>
      <Rate>4.8064</Rate>
      <Difference>-0.0029</Difference>
    </ExchangeRate>
    <ExchangeRate>
      <ISO>BYR</ISO>
      <Amount>10</Amount>
      <Rate>2.3155</Rate>
      <Difference>-0.0014</Difference>
    </ExchangeRate>
    <ExchangeRate>
      <ISO>TJS</ISO>
      <Amount>1</Amount>
      <Rate>180.6679</Rate>
      <Difference>-0.1113</Difference>
    </ExchangeRate>
    <ExchangeRate>
      <ISO>TMT</ISO>
      <Amount>100</Amount>
      <Rate>9.6762</Rate>
      <Difference>-0.0059</Difference>
    </ExchangeRate>
    <ExchangeRate>
      <ISO>GEL</ISO>
      <Amount>1</Amount>
      <Rate>279.5333</Rate>
      <Difference>-0.1723</Difference>
    </ExchangeRate>
  </Rates>
</ExchangeRatesByDateResult>
