<?xml version='1.0' encoding='UTF-8'?>
<ExchangeRatesByDateResult xmlns="http://www.cba.am/" xmlns:soap="http://schemas.xmlsoap.org/soap/envelope/" xmlns:xsi="http://www.w3.org/2001/XMLSchema-instance" xmlns:xsd="http://www.w3.org/2001/XMLSchema">
  <CurrentDate>2004-03-12T00:00:00</CurrentDate>
  <NextAvailableDate>2004-03-15T00:00:00</NextAvailableDate>
  <PreviousAvailableDate>2004-03-11T00:00:00</PreviousAvailableDate>
  <Rates>
    <ExchangeRate>
      <ISO>USD</ISO>
      <Amount>1</Amount>
      <Rate>562.4200</Rate>
      <Difference>-2.6100</Difference>
    </ExchangeRate>
    <ExchangeRate>
      <ISO>GBP</ISO>
      <Amount>1</Amount>
      <Rate>1010.0500</Rate>
      <Difference>-18.5300</Difference>
    </ExchangeRate>
    <ExchangeRate>
      <ISO>AUD</ISO>
      <Amount>1</Amount>
      <Rate>417.7100</Rate>
      <Difference>-9.6200</Difference>
    </ExchangeRate>
    <ExchangeRate>
      <ISO>ARP</ISO>
      <Amount>1</Amount>
      <Rate>192.4400</Rate>
      <Difference>-0.9000</Difference>
    </ExchangeRate>
    <ExchangeRate>
      <ISO>DKK</ISO>
      <Amount>1</Amount>
      <Rate>92.0700</Rate>
      <Difference>0.3100</Difference>
    </ExchangeRate>
    <ExchangeRate>
      <ISO>EGP</ISO>
      <Amount>1</Amount>
      <Rate>91.2500</Rate>
      <Difference>-0.5100</Difference>
    </ExchangeRate>
    <ExchangeRate>
      <ISO>EUR</ISO>
      <Amount>1</Amount>
      <Rate>689.3000</Rate>
      <Difference>-5.6300</Difference>
    </ExchangeRate>
    <ExchangeRate>
      <ISO>SDR</ISO>
      <Amount>1</Amount>
      <Rate>835.2300</Rate>
      <Difference>0.0000</Difference>
    </ExchangeRate>
    <ExchangeRate>
      <ISO>TRL</ISO>
      <Amount>1000</Amount>
      <Rate>4.2900</Rate>
      <Difference>0.0000</Difference>
    </ExchangeRate>
    <ExchangeRate>
      <ISO>IRR</ISO>
      <Amount>100</Amount>
      <Rate>6.6700</Rate>
      <Difference>-0.0400</Difference>
    </ExchangeRate>
    <ExchangeRate>
      <ISO>ILS</ISO>
      <Amount>1</Amount>
      <Rate>125.1200</Rate>
      <Difference>-0.4700</Difference>
    </ExchangeRate>
    <ExchangeRate>
      <ISO>PLZ</ISO>
      <Amount>1</Amount>
      <Rate>143.7200</Rate>
      <Difference>-2.3300</Difference>
    </ExchangeRate>
    <ExchangeRate>
      <ISO>LBP</ISO>
      <Amount>100</Amount>
      <Rate>37.3100</Rate>
      <Difference>-0.1700</Difference>
    </ExchangeRate>
    <ExchangeRate>
      <ISO>CAD</ISO>
      <Amount>1</Amount>
      <Rate>423.8300</Rate>
      <Difference>-4.5500</Difference>
    </ExchangeRate>
    <ExchangeRate>
      <ISO>INR</ISO>
      <Amount>1</Amount>
      <Rate>12.4200</Rate>
      <Difference>-0.0500</Difference>
    </ExchangeRate>
    <ExchangeRate>
      <ISO>HUF</ISO>
      <Amount>10</Amount>
      <Rate>27.1500</Rate>
      <Difference>-0.3500</Difference>
    </ExchangeRate>
    <ExchangeRate>
      <ISO>JPY</ISO>
      <Amount>10</Amount>
      <Rate>50.7600</Rate>
      <Difference>-0.0300</Difference>
    </ExchangeRate>
    <ExchangeRate>
      <ISO>NOK</ISO>
      <Amount>1</Amount>
      <Rate>79.9100</Rate>
      <Difference>-0.8900</Difference>
    </ExchangeRate>
    <ExchangeRate>
      <ISO>SEK</ISO>
      <Amount>1</Amount>
      <Rate>75.3900</Rate>
      <Difference>-0.8100</Difference>
    </ExchangeRate>
    <ExchangeRate>
      <ISO>CHF</ISO>
      <Amount>1</Amount>
      <Rate>438.9600</Rate>
      <Difference>-3.0600</Difference>
    </ExchangeRate>
    <ExchangeRate>
      <ISO>CZK</ISO>
      <Amount>1</Amount>
      <Rate>20.8400</Rate>
      <Difference>-0.2900</Difference>
    </ExchangeRate>
    <ExchangeRate>
      <ISO>CNY</ISO>
      <Amount>1</Amount>
      <Rate>67.9500</Rate>
      <Difference>-0.3100</Difference>
    </ExchangeRate>
    <ExchangeRate>
      <ISO>SGD</ISO>
      <Amount>1</Amount>
      <Rate>328.1300</Rate>
      <Difference>-1.9200</Difference>
    </ExchangeRate>
    <ExchangeRate>
      <ISO>SKK</ISO>
      <Amount>1</Amount>
      <Rate>16.9200</Rate>
      <Difference>-0.1900</Difference>
    </ExchangeRate>
    <ExchangeRate>
      <ISO>KRW</ISO>
      <Amount>100</Amount>
      <Rate>47.9300</Rate>
      <Difference>-0.1900</Difference>
    </ExchangeRate>
    <ExchangeRate>
      <ISO>BRC</ISO>
      <Amount>1</Amount>
      <Rate>194.8300</Rate>
      <Difference>-2.1000</Difference>
    </ExchangeRate>
    <ExchangeRate>
      <ISO>MXN</ISO>
      <Amount>1</Amount>
      <Rate>51.4200</Rate>
      <Difference>-0.0900</Difference>
    </ExchangeRate>
    <ExchangeRate>
      <ISO>SAR</ISO>
      <Amount>1</Amount>
      <Rate>149.9800</Rate>
      <Difference>-0.6900</Difference>
    </ExchangeRate>
    <ExchangeRate>
      <ISO>SYP</ISO>
      <Amount>1</Amount>
      <Rate>10.9000</Rate>
      <Difference>-1.9200</Difference>
    </ExchangeRate>
    <ExchangeRate>
      <ISO>AED</ISO>
      <Amount>1</Amount>
      <Rate>153.1300</Rate>
      <Difference>-0.7100</Difference>
    </ExchangeRate>
    <ExchangeRate>
      <ISO>KWD</ISO>
      <Amount>1</Amount>
      <Rate>1864.1700</Rate>
      <Difference>-8.6500</Difference>
    </ExchangeRate>
    <ExchangeRate>
      <ISO>BGL</ISO>
      <Amount>1</Amount>
      <Rate>353.6700</Rate>
      <Difference>-3.4300</Difference>
    </ExchangeRate>
    <ExchangeRate>
      <ISO>ROL</ISO>
      <Amount>1000</Amount>
      <Rate>16.0700</Rate>
      <Difference>0.5900</Difference>
    </ExchangeRate>
    <ExchangeRate>
      <ISO>ISK</ISO>
      <Amount>1</Amount>
      <Rate>79.3600</Rate>
      <Difference>-0.8700</Difference>
    </ExchangeRate>
    <ExchangeRate>
      <ISO>EEK</ISO>
      <Amount>1</Amount>
      <Rate>43.8600</Rate>
      <Difference>-0.5300</Difference>
    </ExchangeRate>
    <ExchangeRate>
      <ISO>LVL</ISO>
      <Amount>1</Amount>
      <Rate>1033.8600</Rate>
      <Difference>-10.5600</Difference>
    </ExchangeRate>
    <ExchangeRate>
      <ISO>LTL</ISO>
      <Amount>1</Amount>
      <Rate>202.4200</Rate>
      <Difference>-0.9400</Difference>
    </ExchangeRate>
    <ExchangeRate>
      <ISO>KGS</ISO>
      <Amount>1</Amount>
      <Rate>12.9500</Rate>
      <Difference>-0.0600</Difference>
    </ExchangeRate>
    <ExchangeRate>
      <ISO>KZT</ISO>
      <Amount>1</Amount>
      <Rate>38.3500</Rate>
      <Difference>-0.1700</Difference>
    </ExchangeRate>
    <ExchangeRate>
      <ISO>MDL</ISO>
      <Amount>1</Amount>
      <Rate>44.2800</Rate>
      <Difference>-0.1900</Difference>
    </ExchangeRate>
    <ExchangeRate>
      <ISO>RUR</ISO>
      <Amount>1</Amount>
      <Rate>19.6800</Rate>
      <Difference>-0.0900</Difference>
    </ExchangeRate>
    <ExchangeRate>
      <ISO>UAH</ISO>
      <Amount>1</Amount>
      <Rate>105.5300</Rate>
      <Difference>-0.4900</Difference>
    </ExchangeRate>
    <ExchangeRate>
      <ISO>USM</ISO>
      <Amount>1</Amount>
      <Rate>5.6600</Rate>
      <Difference>-0.0300</Difference>
    </ExchangeRate>
    <ExchangeRate>
      <ISO>BYR</ISO>
      <Amount>10</Amount>
      <Rate>2.6100</Rate>
      <Difference>-0.0100</Difference>
    </ExchangeRate>
    <ExchangeRate>
      <ISO>TJS</ISO>
      <Amount>1</Amount>
      <Rate>201.5800</Rate>
      <Difference>-0.9400</Difference>
    </ExchangeRate>
    <ExchangeRate>
      <ISO>TMT</ISO>
      <Amount>100</Amount>
      <Rate>10.8200</Rate>
      <Difference>-0.0500</Difference>
    </ExchangeRate>
    <ExchangeRate>
      <ISO>GEL</ISO>
      <Amount>1</Amount>
      <Rate>277.0500</Rate>
      <Difference>-12.7100</Difference>
    </ExchangeRate>
  </Rates>
</ExchangeRatesByDateResult>
