<?xml version='1.0' encoding='UTF-8'?>
<ExchangeRatesByDateResult xmlns="http://www.cba.am/" xmlns:soap="http://schemas.xmlsoap.org/soap/envelope/" xmlns:xsi="http://www.w3.org/2001/XMLSchema-instance" xmlns:xsd="http://www.w3.org/2001/XMLSchema">
  <CurrentDate>2006-11-03T00:00:00</CurrentDate>
  <NextAvailableDate>2006-11-06T00:00:00</NextAvailableDate>
  <PreviousAvailableDate>2006-11-02T00:00:00</PreviousAvailableDate>
  <Rates>
    <ExchangeRate>
      <ISO>USD</ISO>
      <Amount>1</Amount>
      <Rate>381.2400</Rate>
      <Difference>0.6200</Difference>
    </ExchangeRate>
    <ExchangeRate>
      <ISO>GBP</ISO>
      <Amount>1</Amount>
      <Rate>727.4385</Rate>
      <Difference>1.0462</Difference>
    </ExchangeRate>
    <ExchangeRate>
      <ISO>AUD</ISO>
      <Amount>1</Amount>
      <Rate>294.3173</Rate>
      <Difference>-0.4729</Difference>
    </ExchangeRate>
    <ExchangeRate>
      <ISO>ATS</ISO>
      <Amount>1</Amount>
      <Rate>0.0000</Rate>
      <Difference>0.0000</Difference>
    </ExchangeRate>
    <ExchangeRate>
      <ISO>ARP</ISO>
      <Amount>1</Amount>
      <Rate>122.8321</Rate>
      <Difference>0.5445</Difference>
    </ExchangeRate>
    <ExchangeRate>
      <ISO>BEF</ISO>
      <Amount>10</Amount>
      <Rate>0.0000</Rate>
      <Difference>0.0000</Difference>
    </ExchangeRate>
    <ExchangeRate>
      <ISO>DEM</ISO>
      <Amount>1</Amount>
      <Rate>0.0000</Rate>
      <Difference>0.0000</Difference>
    </ExchangeRate>
    <ExchangeRate>
      <ISO>DKK</ISO>
      <Amount>1</Amount>
      <Rate>65.2406</Rate>
      <Difference>0.4101</Difference>
    </ExchangeRate>
    <ExchangeRate>
      <ISO>EGP</ISO>
      <Amount>1</Amount>
      <Rate>61.1574</Rate>
      <Difference>0.0994</Difference>
    </ExchangeRate>
    <ExchangeRate>
      <ISO>EUR</ISO>
      <Amount>1</Amount>
      <Rate>486.7291</Rate>
      <Difference>1.1722</Difference>
    </ExchangeRate>
    <ExchangeRate>
      <ISO>SDR</ISO>
      <Amount>1</Amount>
      <Rate>563.2400</Rate>
      <Difference>0.0000</Difference>
    </ExchangeRate>
    <ExchangeRate>
      <ISO>TRL</ISO>
      <Amount>1</Amount>
      <Rate>262.5801</Rate>
      <Difference>1.3985</Difference>
    </ExchangeRate>
    <ExchangeRate>
      <ISO>IRR</ISO>
      <Amount>100</Amount>
      <Rate>4.2163</Rate>
      <Difference>0.0068</Difference>
    </ExchangeRate>
    <ExchangeRate>
      <ISO>ESP</ISO>
      <Amount>10</Amount>
      <Rate>0.0000</Rate>
      <Difference>0.0000</Difference>
    </ExchangeRate>
    <ExchangeRate>
      <ISO>ILS</ISO>
      <Amount>1</Amount>
      <Rate>89.4720</Rate>
      <Difference>0.7080</Difference>
    </ExchangeRate>
    <ExchangeRate>
      <ISO>ITL</ISO>
      <Amount>100</Amount>
      <Rate>0.0000</Rate>
      <Difference>0.0000</Difference>
    </ExchangeRate>
    <ExchangeRate>
      <ISO>PLZ</ISO>
      <Amount>1</Amount>
      <Rate>125.9681</Rate>
      <Difference>1.7084</Difference>
    </ExchangeRate>
    <ExchangeRate>
      <ISO>LBP</ISO>
      <Amount>100</Amount>
      <Rate>25.2896</Rate>
      <Difference>0.0412</Difference>
    </ExchangeRate>
    <ExchangeRate>
      <ISO>CAD</ISO>
      <Amount>1</Amount>
      <Rate>336.9333</Rate>
      <Difference>-2.0887</Difference>
    </ExchangeRate>
    <ExchangeRate>
      <ISO>INR</ISO>
      <Amount>1</Amount>
      <Rate>8.4852</Rate>
      <Difference>0.0138</Difference>
    </ExchangeRate>
    <ExchangeRate>
      <ISO>NLG</ISO>
      <Amount>1</Amount>
      <Rate>0.0000</Rate>
      <Difference>0.0000</Difference>
    </ExchangeRate>
    <ExchangeRate>
      <ISO>GRD</ISO>
      <Amount>10</Amount>
      <Rate>0.0000</Rate>
      <Difference>0.0000</Difference>
    </ExchangeRate>
    <ExchangeRate>
      <ISO>HUF</ISO>
      <Amount>10</Amount>
      <Rate>18.7590</Rate>
      <Difference>0.3199</Difference>
    </ExchangeRate>
    <ExchangeRate>
      <ISO>JPY</ISO>
      <Amount>10</Amount>
      <Rate>32.5068</Rate>
      <Difference>-0.0332</Difference>
    </ExchangeRate>
    <ExchangeRate>
      <ISO>NOK</ISO>
      <Amount>1</Amount>
      <Rate>58.5928</Rate>
      <Difference>0.5953</Difference>
    </ExchangeRate>
    <ExchangeRate>
      <ISO>SEK</ISO>
      <Amount>1</Amount>
      <Rate>52.8956</Rate>
      <Difference>0.1864</Difference>
    </ExchangeRate>
    <ExchangeRate>
      <ISO>CHF</ISO>
      <Amount>1</Amount>
      <Rate>306.5045</Rate>
      <Difference>0.8729</Difference>
    </ExchangeRate>
    <ExchangeRate>
      <ISO>CZK</ISO>
      <Amount>1</Amount>
      <Rate>17.3291</Rate>
      <Difference>0.2049</Difference>
    </ExchangeRate>
    <ExchangeRate>
      <ISO>CNY</ISO>
      <Amount>1</Amount>
      <Rate>48.4114</Rate>
      <Difference>0.0603</Difference>
    </ExchangeRate>
    <ExchangeRate>
      <ISO>PTE</ISO>
      <Amount>10</Amount>
      <Rate>0.0000</Rate>
      <Difference>0.0000</Difference>
    </ExchangeRate>
    <ExchangeRate>
      <ISO>SGD</ISO>
      <Amount>1</Amount>
      <Rate>244.0561</Rate>
      <Difference>-0.2600</Difference>
    </ExchangeRate>
    <ExchangeRate>
      <ISO>SKK</ISO>
      <Amount>1</Amount>
      <Rate>13.3263</Rate>
      <Difference>0.0216</Difference>
    </ExchangeRate>
    <ExchangeRate>
      <ISO>FIM</ISO>
      <Amount>1</Amount>
      <Rate>0.0000</Rate>
      <Difference>0.0000</Difference>
    </ExchangeRate>
    <ExchangeRate>
      <ISO>FRF</ISO>
      <Amount>1</Amount>
      <Rate>0.0000</Rate>
      <Difference>0.0000</Difference>
    </ExchangeRate>
    <ExchangeRate>
      <ISO>KRW</ISO>
      <Amount>100</Amount>
      <Rate>37.9230</Rate>
      <Difference>0.0617</Difference>
    </ExchangeRate>
    <ExchangeRate>
      <ISO>BRC</ISO>
      <Amount>1</Amount>
      <Rate>178.0663</Rate>
      <Difference>-0.0599</Difference>
    </ExchangeRate>
    <ExchangeRate>
      <ISO>MXN</ISO>
      <Amount>1</Amount>
      <Rate>35.4810</Rate>
      <Difference>0.1205</Difference>
    </ExchangeRate>
    <ExchangeRate>
      <ISO>SAR</ISO>
      <Amount>1</Amount>
      <Rate>101.6559</Rate>
      <Difference>0.1654</Difference>
    </ExchangeRate>
    <ExchangeRate>
      <ISO>SYP</ISO>
      <Amount>1</Amount>
      <Rate>7.3020</Rate>
      <Difference>0.0118</Difference>
    </ExchangeRate>
    <ExchangeRate>
      <ISO>AED</ISO>
      <Amount>1</Amount>
      <Rate>103.7981</Rate>
      <Difference>0.1688</Difference>
    </ExchangeRate>
    <ExchangeRate>
      <ISO>KWD</ISO>
      <Amount>1</Amount>
      <Rate>1276.7582</Rate>
      <Difference>2.0764</Difference>
    </ExchangeRate>
    <ExchangeRate>
      <ISO>BGL</ISO>
      <Amount>1</Amount>
      <Rate>248.6661</Rate>
      <Difference>1.5921</Difference>
    </ExchangeRate>
    <ExchangeRate>
      <ISO>RON</ISO>
      <Amount>1</Amount>
      <Rate>138.4062</Rate>
      <Difference>0.2902</Difference>
    </ExchangeRate>
    <ExchangeRate>
      <ISO>ISK</ISO>
      <Amount>1</Amount>
      <Rate>56.3298</Rate>
      <Difference>0.0167</Difference>
    </ExchangeRate>
    <ExchangeRate>
      <ISO>EEK</ISO>
      <Amount>1</Amount>
      <Rate>31.1041</Rate>
      <Difference>0.1042</Difference>
    </ExchangeRate>
    <ExchangeRate>
      <ISO>LVL</ISO>
      <Amount>1</Amount>
      <Rate>691.9056</Rate>
      <Difference>3.6235</Difference>
    </ExchangeRate>
    <ExchangeRate>
      <ISO>LTL</ISO>
      <Amount>1</Amount>
      <Rate>140.1103</Rate>
      <Difference>-0.1846</Difference>
    </ExchangeRate>
    <ExchangeRate>
      <ISO>KGS</ISO>
      <Amount>1</Amount>
      <Rate>9.7545</Rate>
      <Difference>0.0159</Difference>
    </ExchangeRate>
    <ExchangeRate>
      <ISO>KZT</ISO>
      <Amount>10</Amount>
      <Rate>29.8217</Rate>
      <Difference>0.0485</Difference>
    </ExchangeRate>
    <ExchangeRate>
      <ISO>MDL</ISO>
      <Amount>1</Amount>
      <Rate>28.6425</Rate>
      <Difference>0.0466</Difference>
    </ExchangeRate>
    <ExchangeRate>
      <ISO>RUR</ISO>
      <Amount>1</Amount>
      <Rate>14.2639</Rate>
      <Difference>0.0237</Difference>
    </ExchangeRate>
    <ExchangeRate>
      <ISO>UAH</ISO>
      <Amount>1</Amount>
      <Rate>75.4931</Rate>
      <Difference>0.1228</Difference>
    </ExchangeRate>
    <ExchangeRate>
      <ISO>USM</ISO>
      <Amount>1</Amount>
      <Rate>3.0944</Rate>
      <Difference>0.0051</Difference>
    </ExchangeRate>
    <ExchangeRate>
      <ISO>BYR</ISO>
      <Amount>10</Amount>
      <Rate>1.7807</Rate>
      <Difference>0.0029</Difference>
    </ExchangeRate>
    <ExchangeRate>
      <ISO>TJS</ISO>
      <Amount>1</Amount>
      <Rate>112.4602</Rate>
      <Difference>0.1829</Difference>
    </ExchangeRate>
    <ExchangeRate>
      <ISO>TMT</ISO>
      <Amount>10</Amount>
      <Rate>7.3315</Rate>
      <Difference>0.0119</Difference>
    </ExchangeRate>
    <ExchangeRate>
      <ISO>GEL</ISO>
      <Amount>1</Amount>
      <Rate>219.4187</Rate>
      <Difference>0.3568</Difference>
    </ExchangeRate>
    <ExchangeRate>
      <ISO>HKD</ISO>
      <Amount>1</Amount>
      <Rate>49.0190</Rate>
      <Difference>0.0875</Difference>
    </ExchangeRate>
  </Rates>
</ExchangeRatesByDateResult>
