<?xml version='1.0' encoding='UTF-8'?>
<ExchangeRatesByDateResult xmlns="http://www.cba.am/" xmlns:soap="http://schemas.xmlsoap.org/soap/envelope/" xmlns:xsi="http://www.w3.org/2001/XMLSchema-instance" xmlns:xsd="http://www.w3.org/2001/XMLSchema">
  <CurrentDate>2009-03-02T00:00:00</CurrentDate>
  <NextAvailableDate>2009-03-03T00:00:00</NextAvailableDate>
  <PreviousAvailableDate>2009-02-28T00:00:00</PreviousAvailableDate>
  <Rates>
    <ExchangeRate>
      <ISO>USD</ISO>
      <Amount>1</Amount>
      <Rate>305.7500</Rate>
      <Difference>-0.0800</Difference>
    </ExchangeRate>
    <ExchangeRate>
      <ISO>GBP</ISO>
      <Amount>1</Amount>
      <Rate>434.5319</Rate>
      <Difference>0.6968</Difference>
    </ExchangeRate>
    <ExchangeRate>
      <ISO>AUD</ISO>
      <Amount>1</Amount>
      <Rate>194.3041</Rate>
      <Difference>-1.4118</Difference>
    </ExchangeRate>
    <ExchangeRate>
      <ISO>ATS</ISO>
      <Amount>1</Amount>
      <Rate>0.0000</Rate>
      <Difference>0.0000</Difference>
    </ExchangeRate>
    <ExchangeRate>
      <ISO>ARP</ISO>
      <Amount>1</Amount>
      <Rate>85.7644</Rate>
      <Difference>-0.3000</Difference>
    </ExchangeRate>
    <ExchangeRate>
      <ISO>BEF</ISO>
      <Amount>10</Amount>
      <Rate>0.0000</Rate>
      <Difference>0.0000</Difference>
    </ExchangeRate>
    <ExchangeRate>
      <ISO>DEM</ISO>
      <Amount>1</Amount>
      <Rate>0.0000</Rate>
      <Difference>0.0000</Difference>
    </ExchangeRate>
    <ExchangeRate>
      <ISO>DKK</ISO>
      <Amount>1</Amount>
      <Rate>51.7796</Rate>
      <Difference>-0.2086</Difference>
    </ExchangeRate>
    <ExchangeRate>
      <ISO>EGP</ISO>
      <Amount>1</Amount>
      <Rate>54.3846</Rate>
      <Difference>-0.0820</Difference>
    </ExchangeRate>
    <ExchangeRate>
      <ISO>EUR</ISO>
      <Amount>1</Amount>
      <Rate>385.7067</Rate>
      <Difference>-1.5842</Difference>
    </ExchangeRate>
    <ExchangeRate>
      <ISO>SDR</ISO>
      <Amount>1</Amount>
      <Rate>448.7600</Rate>
      <Difference>0.0000</Difference>
    </ExchangeRate>
    <ExchangeRate>
      <ISO>TRY</ISO>
      <Amount>1</Amount>
      <Rate>181.1959</Rate>
      <Difference>-0.9759</Difference>
    </ExchangeRate>
    <ExchangeRate>
      <ISO>IEP</ISO>
      <Amount>1</Amount>
      <Rate>0.0000</Rate>
      <Difference>0.0000</Difference>
    </ExchangeRate>
    <ExchangeRate>
      <ISO>IRR</ISO>
      <Amount>100</Amount>
      <Rate>3.0914</Rate>
      <Difference>-0.0623</Difference>
    </ExchangeRate>
    <ExchangeRate>
      <ISO>ESP</ISO>
      <Amount>10</Amount>
      <Rate>0.0000</Rate>
      <Difference>0.0000</Difference>
    </ExchangeRate>
    <ExchangeRate>
      <ISO>ILS</ISO>
      <Amount>1</Amount>
      <Rate>72.7111</Rate>
      <Difference>-0.3945</Difference>
    </ExchangeRate>
    <ExchangeRate>
      <ISO>ITL</ISO>
      <Amount>100</Amount>
      <Rate>0.0000</Rate>
      <Difference>0.0000</Difference>
    </ExchangeRate>
    <ExchangeRate>
      <ISO>PLN</ISO>
      <Amount>1</Amount>
      <Rate>83.1792</Rate>
      <Difference>-1.0436</Difference>
    </ExchangeRate>
    <ExchangeRate>
      <ISO>LBP</ISO>
      <Amount>100</Amount>
      <Rate>20.3393</Rate>
      <Difference>-0.0053</Difference>
    </ExchangeRate>
    <ExchangeRate>
      <ISO>CAD</ISO>
      <Amount>1</Amount>
      <Rate>239.2447</Rate>
      <Difference>-3.9465</Difference>
    </ExchangeRate>
    <ExchangeRate>
      <ISO>INR</ISO>
      <Amount>1</Amount>
      <Rate>5.9082</Rate>
      <Difference>-0.1204</Difference>
    </ExchangeRate>
    <ExchangeRate>
      <ISO>NLG</ISO>
      <Amount>1</Amount>
      <Rate>0.0000</Rate>
      <Difference>0.0000</Difference>
    </ExchangeRate>
    <ExchangeRate>
      <ISO>GRD</ISO>
      <Amount>10</Amount>
      <Rate>0.0000</Rate>
      <Difference>0.0000</Difference>
    </ExchangeRate>
    <ExchangeRate>
      <ISO>HUF</ISO>
      <Amount>10</Amount>
      <Rate>12.5818</Rate>
      <Difference>-0.4951</Difference>
    </ExchangeRate>
    <ExchangeRate>
      <ISO>JPY</ISO>
      <Amount>10</Amount>
      <Rate>31.4322</Rate>
      <Difference>-0.0140</Difference>
    </ExchangeRate>
    <ExchangeRate>
      <ISO>NOK</ISO>
      <Amount>1</Amount>
      <Rate>42.8581</Rate>
      <Difference>-0.9690</Difference>
    </ExchangeRate>
    <ExchangeRate>
      <ISO>SEK</ISO>
      <Amount>1</Amount>
      <Rate>33.4211</Rate>
      <Difference>-0.4696</Difference>
    </ExchangeRate>
    <ExchangeRate>
      <ISO>CHF</ISO>
      <Amount>1</Amount>
      <Rate>260.5898</Rate>
      <Difference>-0.2015</Difference>
    </ExchangeRate>
    <ExchangeRate>
      <ISO>CZK</ISO>
      <Amount>1</Amount>
      <Rate>13.5867</Rate>
      <Difference>-0.1497</Difference>
    </ExchangeRate>
    <ExchangeRate>
      <ISO>CNY</ISO>
      <Amount>1</Amount>
      <Rate>44.7075</Rate>
      <Difference>-0.0235</Difference>
    </ExchangeRate>
    <ExchangeRate>
      <ISO>PTE</ISO>
      <Amount>10</Amount>
      <Rate>0.0000</Rate>
      <Difference>0.0000</Difference>
    </ExchangeRate>
    <ExchangeRate>
      <ISO>SGD</ISO>
      <Amount>1</Amount>
      <Rate>196.7501</Rate>
      <Difference>-2.9875</Difference>
    </ExchangeRate>
    <ExchangeRate>
      <ISO>SKK</ISO>
      <Amount>1</Amount>
      <Rate>0.0000</Rate>
      <Difference>0.0000</Difference>
    </ExchangeRate>
    <ExchangeRate>
      <ISO>FIM</ISO>
      <Amount>1</Amount>
      <Rate>0.0000</Rate>
      <Difference>0.0000</Difference>
    </ExchangeRate>
    <ExchangeRate>
      <ISO>FRF</ISO>
      <Amount>1</Amount>
      <Rate>0.0000</Rate>
      <Difference>0.0000</Difference>
    </ExchangeRate>
    <ExchangeRate>
      <ISO>KRW</ISO>
      <Amount>100</Amount>
      <Rate>19.4665</Rate>
      <Difference>-0.6864</Difference>
    </ExchangeRate>
    <ExchangeRate>
      <ISO>BRC</ISO>
      <Amount>1</Amount>
      <Rate>128.1111</Rate>
      <Difference>-0.9801</Difference>
    </ExchangeRate>
    <ExchangeRate>
      <ISO>MXN</ISO>
      <Amount>1</Amount>
      <Rate>20.2557</Rate>
      <Difference>-0.2870</Difference>
    </ExchangeRate>
    <ExchangeRate>
      <ISO>SAR</ISO>
      <Amount>1</Amount>
      <Rate>81.5051</Rate>
      <Difference>-0.0409</Difference>
    </ExchangeRate>
    <ExchangeRate>
      <ISO>SYP</ISO>
      <Amount>1</Amount>
      <Rate>6.4819</Rate>
      <Difference>-0.0934</Difference>
    </ExchangeRate>
    <ExchangeRate>
      <ISO>AED</ISO>
      <Amount>1</Amount>
      <Rate>83.2448</Rate>
      <Difference>-0.0218</Difference>
    </ExchangeRate>
    <ExchangeRate>
      <ISO>KWD</ISO>
      <Amount>1</Amount>
      <Rate>1036.4407</Rate>
      <Difference>-5.5695</Difference>
    </ExchangeRate>
    <ExchangeRate>
      <ISO>BGL</ISO>
      <Amount>1</Amount>
      <Rate>197.6661</Rate>
      <Difference>-2.4059</Difference>
    </ExchangeRate>
    <ExchangeRate>
      <ISO>RON</ISO>
      <Amount>1</Amount>
      <Rate>90.3223</Rate>
      <Difference>-1.4469</Difference>
    </ExchangeRate>
    <ExchangeRate>
      <ISO>ISK</ISO>
      <Amount>1</Amount>
      <Rate>26.6774</Rate>
      <Difference>-0.3848</Difference>
    </ExchangeRate>
    <ExchangeRate>
      <ISO>EEK</ISO>
      <Amount>1</Amount>
      <Rate>24.6265</Rate>
      <Difference>-0.6070</Difference>
    </ExchangeRate>
    <ExchangeRate>
      <ISO>LVL</ISO>
      <Amount>1</Amount>
      <Rate>543.2658</Rate>
      <Difference>-2.9567</Difference>
    </ExchangeRate>
    <ExchangeRate>
      <ISO>LTL</ISO>
      <Amount>1</Amount>
      <Rate>111.5998</Rate>
      <Difference>-0.5902</Difference>
    </ExchangeRate>
    <ExchangeRate>
      <ISO>KGS</ISO>
      <Amount>1</Amount>
      <Rate>7.4482</Rate>
      <Difference>-0.0020</Difference>
    </ExchangeRate>
    <ExchangeRate>
      <ISO>KZT</ISO>
      <Amount>10</Amount>
      <Rate>20.3481</Rate>
      <Difference>-0.0406</Difference>
    </ExchangeRate>
    <ExchangeRate>
      <ISO>MDL</ISO>
      <Amount>1</Amount>
      <Rate>28.3759</Rate>
      <Difference>-0.0933</Difference>
    </ExchangeRate>
    <ExchangeRate>
      <ISO>RUB</ISO>
      <Amount>1</Amount>
      <Rate>8.4632</Rate>
      <Difference>-0.0855</Difference>
    </ExchangeRate>
    <ExchangeRate>
      <ISO>UAH</ISO>
      <Amount>1</Amount>
      <Rate>35.7116</Rate>
      <Difference>-0.2234</Difference>
    </ExchangeRate>
    <ExchangeRate>
      <ISO>UZS</ISO>
      <Amount>10</Amount>
      <Rate>2.1708</Rate>
      <Difference>-0.0006</Difference>
    </ExchangeRate>
    <ExchangeRate>
      <ISO>BYR</ISO>
      <Amount>10</Amount>
      <Rate>1.0680</Rate>
      <Difference>-0.0015</Difference>
    </ExchangeRate>
    <ExchangeRate>
      <ISO>TJS</ISO>
      <Amount>1</Amount>
      <Rate>81.7881</Rate>
      <Difference>-0.0214</Difference>
    </ExchangeRate>
    <ExchangeRate>
      <ISO>TMT</ISO>
      <Amount>10</Amount>
      <Rate>2.1464</Rate>
      <Difference>-0.0005</Difference>
    </ExchangeRate>
    <ExchangeRate>
      <ISO>GEL</ISO>
      <Amount>1</Amount>
      <Rate>181.5618</Rate>
      <Difference>-0.3716</Difference>
    </ExchangeRate>
    <ExchangeRate>
      <ISO>HKD</ISO>
      <Amount>1</Amount>
      <Rate>39.4191</Rate>
      <Difference>-0.0240</Difference>
    </ExchangeRate>
  </Rates>
</ExchangeRatesByDateResult>
